{
  "cities": [
    {
      "cityName": "Lisbon",
      "country": "Portugal",
      "emoji": "🇵🇹",
      "date": "2027-10-31T15:59:59.138Z",
      "notes": "My favorite city so far!",
      "position": {
        "lat": 38.727881642324164,
        "lng": -9.140900099907554
      },
      "id": "73930385"
    },
    {
      "cityName": "Madrid",
      "country": "Spain",
      "emoji": "🇪🇸",
      "date": "2027-07-15T08:22:53.976Z",
      "notes": "",
      "position": {
        "lat": 40.46635901755316,
        "lng": -3.7133789062500004
      },
      "id": "17806751"
    },
    {
      "cityName": "Berlin",
      "country": "Germany",
      "emoji": "🇩🇪",
      "date": "2027-02-12T09:24:11.863Z",
      "notes": "Amazing 😃",
      "position": {
        "lat": 52.53586782505711,
        "lng": 13.376933665713324
      },
      "id": "98443197"
    },
    {
      "id": "bf65",
      "cityName": "Ottawa",
      "country": "Canada",
      "emoji": "🇨🇦",
      "date": "2024-10-22T08:31:38.000Z",
      "notes": "Great target",
      "position": {
        "lat": "45.3521452458518",
        "lng": "-75.59692382812501"
      }
    },
    {
      "id": "623c",
      "cityName": "Ottawa",
      "country": "Canada",
      "emoji": "🇨🇦",
      "date": "2023-05-14T07:48:20.000Z",
      "notes": "Spring",
      "position": {
        "lat": "45.41977448702922",
        "lng": "-75.68837753251805"
      }
    },
    {
      "id": "804e",
      "cityName": "Ostermundigen",
      "country": "Switzerland",
      "emoji": "🇨🇭",
      "date": "2026-10-14T07:49:35.000Z",
      "notes": "",
      "position": {
        "lat": "46.95586136168301",
        "lng": "7.506895596961886"
      }
    },
    {
      "id": "bcc3",
      "cityName": "Lyon",
      "country": "France",
      "emoji": "🇫🇷",
      "date": "2025-11-07T23:54:47.000Z",
      "notes": "",
      "position": {
        "lat": "45.723440790877945",
        "lng": "4.887050773909079"
      }
    }
  ]
}